database/__init__.py
database/function.py
database/models.py
log_conf/__init__.py
log_conf/client_log_config.py
log_conf/server_log_config.py
server/__init__.py
server/server.py
server/server_gui.py
server/test_server.py
gb_test_server-0.0.1.dist-info/METADATA
gb_test_server-0.0.1.dist-info/WHEEL
gb_test_server-0.0.1.dist-info/top_level.txt
gb_test_server-0.0.1.dist-info/RECORD
